bibos_client/__init__.py
bibos_client/admin_client.py
bibos_client/bibos_proxy_setup.py
bibos_client/gateway.py
bibos_client/jobmanager.py
bibos_client/utils.py
bibos_client-0.0.6.0.data/scripts/admin_connect.sh
bibos_client-0.0.6.0.data/scripts/bibos_find_gateway
bibos_client-0.0.6.0.data/scripts/bibos_push_config_keys
bibos_client-0.0.6.0.data/scripts/bibos_register_in_admin
bibos_client-0.0.6.0.data/scripts/bibos_upload_dist_packages
bibos_client-0.0.6.0.data/scripts/bibos_upload_packages
bibos_client-0.0.6.0.data/scripts/jobmanager
bibos_client-0.0.6.0.data/scripts/register_new_bibos_client.sh
bibos_client-0.0.6.0.dist-info/LICENSE
bibos_client-0.0.6.0.dist-info/METADATA
bibos_client-0.0.6.0.dist-info/WHEEL
bibos_client-0.0.6.0.dist-info/top_level.txt
bibos_client-0.0.6.0.dist-info/RECORD
