Metadata-Version: 2.1
Name: bibos-client
Version: 0.0.6.0
Summary: Clients for the BibOS system
Home-page: https://github.com/magenta-aps/
Author: C. Agger and J.U.B. Krag, Magenta ApS
Author-email: carstena@magenta-aps.dk
License: GPLv3
Platform: UNKNOWN
Requires-Dist: bibos-utils
